{
    "RFClassifier": {
        "class_weight": {
            "false": 1,
            "true": 4
        },
        "criterion": "entropy",
        "max_depth": 10,
        "max_features": "log2",
        "min_samples_leaf": 6,
        "min_samples_split": 3,
        "n_estimators": 241
    },
    "RFRegressor": {
        "criterion": "squared_error",
        "max_depth": 11,
        "max_features": "sqrt",
        "min_samples_leaf": 3,
        "min_samples_split": 8,
        "n_estimators": 70
    }
}